tablescope/__init__.py
tablescope/cli.py
tablescope/static/table_view.html.jinja
tablescope/static/tabulator.min.css
tablescope/static/tabulator.min.js
tablescope-0.1.12.dist-info/METADATA
tablescope-0.1.12.dist-info/WHEEL
tablescope-0.1.12.dist-info/entry_points.txt
tablescope-0.1.12.dist-info/licenses/LICENSE.txt
tablescope-0.1.12.dist-info/RECORD
