Metadata-Version: 2.3
Name: tablescope
Version: 0.1.12
Summary: View your data frames in a browser
Author-email: "Samuel S. Watson" <samuel.s.watson@gmail.com>
License: MIT
Requires-Python: >=3.9
Requires-Dist: narwhals>=1.25.2
